[
  {
    "epoch": 1,
    "train": {
      "loss": 1.3156527740690442,
      "acc": 0.383111111190584,
      "macro_f1": 0.3770297364828959,
      "routing_entropy": 3.2972228394614325
    },
    "val": {
      "loss": 1.285130563735962,
      "acc": 0.3839999951124191,
      "macro_f1": 0.27877075660657746,
      "routing_entropy": 3.2880886793136597
    },
    "test": {
      "loss": 1.3181172370910645,
      "acc": 0.34600000143051146,
      "macro_f1": 0.23850825093602848,
      "routing_entropy": 3.2940438389778137
    },
    "expert_usage": {
      "moe_0": {
        "selection_counts": [
          6,
          314,
          1522,
          1800,
          145,
          10,
          1149,
          79,
          67,
          29,
          958,
          38,
          0,
          2,
          1722,
          1912,
          27,
          722,
          79,
          63,
          1209,
          1,
          1857,
          1280,
          946,
          1107,
          1,
          2562,
          35,
          3,
          1355,
          3000
        ],
        "fixed_selection_counts": [
          0,
          0,
          0,
          0,
          0,
          0,
          0,
          0,
          0,
          0,
          0,
          0,
          0,
          0,
          0,
          0,
          0,
          0,
          0,
          0,
          0,
          0,
          0,
          0,
          0,
          0,
          0,
          0,
          0,
          0,
          0,
          3000
        ],
        "dynamic_selection_counts": [
          6,
          314,
          1522,
          1800,
          145,
          10,
          1149,
          79,
          67,
          29,
          958,
          38,
          0,
          2,
          1722,
          1912,
          27,
          722,
          79,
          63,
          1209,
          1,
          1857,
          1280,
          946,
          1107,
          1,
          2562,
          35,
          3,
          1355,
          0
        ]
      }
    }
  },
  {
    "epoch": 2,
    "train": {
      "loss": 1.2219816176096598,
      "acc": 0.4395555560853746,
      "macro_f1": 0.4289757919757912,
      "routing_entropy": 3.1428364912668862
    },
    "val": {
      "loss": 1.2581064348220825,
      "acc": 0.38799998044967654,
      "macro_f1": 0.38363943159728053,
      "routing_entropy": 3.0176690816879272
    },
    "test": {
      "loss": 1.2818087491989136,
      "acc": 0.4220000002384186,
      "macro_f1": 0.4207758541709822,
      "routing_entropy": 3.015085816383362
    },
    "expert_usage": {
      "moe_0": {
        "selection_counts": [
          0,
          129,
          2170,
          1915,
          0,
          0,
          696,
          0,
          0,
          0,
          922,
          30,
          4,
          0,
          1861,
          1806,
          0,
          1062,
          73,
          53,
          1160,
          0,
          1737,
          896,
          771,
          1178,
          0,
          2783,
          0,
          0,
          1754,
          3000
        ],
        "fixed_selection_counts": [
          0,
          0,
          0,
          0,
          0,
          0,
          0,
          0,
          0,
          0,
          0,
          0,
          0,
          0,
          0,
          0,
          0,
          0,
          0,
          0,
          0,
          0,
          0,
          0,
          0,
          0,
          0,
          0,
          0,
          0,
          0,
          3000
        ],
        "dynamic_selection_counts": [
          0,
          129,
          2170,
          1915,
          0,
          0,
          696,
          0,
          0,
          0,
          922,
          30,
          4,
          0,
          1861,
          1806,
          0,
          1062,
          73,
          53,
          1160,
          0,
          1737,
          896,
          771,
          1178,
          0,
          2783,
          0,
          0,
          1754,
          0
        ]
      }
    }
  },
  {
    "epoch": 3,
    "train": {
      "loss": 1.2059118729697333,
      "acc": 0.4520000005298191,
      "macro_f1": 0.4331734313165236,
      "routing_entropy": 3.0493812561035156
    },
    "val": {
      "loss": 1.1811567163467407,
      "acc": 0.41599999809265137,
      "macro_f1": 0.37117867792342996,
      "routing_entropy": 2.960054397583008
    },
    "test": {
      "loss": 1.2695242862701417,
      "acc": 0.36800000166893004,
      "macro_f1": 0.3143470217326767,
      "routing_entropy": 2.965152382850647
    },
    "expert_usage": {
      "moe_0": {
        "selection_counts": [
          0,
          3,
          2396,
          1658,
          0,
          0,
          1104,
          0,
          0,
          0,
          858,
          25,
          0,
          0,
          1768,
          1668,
          0,
          1340,
          114,
          92,
          1541,
          0,
          1620,
          551,
          635,
          1209,
          0,
          2775,
          19,
          0,
          1624,
          3000
        ],
        "fixed_selection_counts": [
          0,
          0,
          0,
          0,
          0,
          0,
          0,
          0,
          0,
          0,
          0,
          0,
          0,
          0,
          0,
          0,
          0,
          0,
          0,
          0,
          0,
          0,
          0,
          0,
          0,
          0,
          0,
          0,
          0,
          0,
          0,
          3000
        ],
        "dynamic_selection_counts": [
          0,
          3,
          2396,
          1658,
          0,
          0,
          1104,
          0,
          0,
          0,
          858,
          25,
          0,
          0,
          1768,
          1668,
          0,
          1340,
          114,
          92,
          1541,
          0,
          1620,
          551,
          635,
          1209,
          0,
          2775,
          19,
          0,
          1624,
          0
        ]
      }
    }
  },
  {
    "epoch": 4,
    "train": {
      "loss": 1.1892299950917562,
      "acc": 0.44444444505373637,
      "macro_f1": 0.4341761156970453,
      "routing_entropy": 3.042714516321818
    },
    "val": {
      "loss": 1.2433857374191284,
      "acc": 0.3839999930858612,
      "macro_f1": 0.3368152342680668,
      "routing_entropy": 3.003337025642395
    },
    "test": {
      "loss": 1.268483127593994,
      "acc": 0.3759999985694885,
      "macro_f1": 0.3507191119761218,
      "routing_entropy": 3.0082238912582397
    },
    "expert_usage": {
      "moe_0": {
        "selection_counts": [
          1,
          9,
          2456,
          1636,
          0,
          0,
          978,
          0,
          0,
          0,
          626,
          11,
          0,
          0,
          1842,
          1709,
          0,
          1127,
          141,
          2,
          1626,
          2,
          1707,
          675,
          618,
          1251,
          0,
          2615,
          39,
          0,
          1929,
          3000
        ],
        "fixed_selection_counts": [
          0,
          0,
          0,
          0,
          0,
          0,
          0,
          0,
          0,
          0,
          0,
          0,
          0,
          0,
          0,
          0,
          0,
          0,
          0,
          0,
          0,
          0,
          0,
          0,
          0,
          0,
          0,
          0,
          0,
          0,
          0,
          3000
        ],
        "dynamic_selection_counts": [
          1,
          9,
          2456,
          1636,
          0,
          0,
          978,
          0,
          0,
          0,
          626,
          11,
          0,
          0,
          1842,
          1709,
          0,
          1127,
          141,
          2,
          1626,
          2,
          1707,
          675,
          618,
          1251,
          0,
          2615,
          39,
          0,
          1929,
          0
        ]
      }
    }
  },
  {
    "epoch": 5,
    "train": {
      "loss": 1.165385458310445,
      "acc": 0.47200000052981905,
      "macro_f1": 0.459239331335543,
      "routing_entropy": 3.0494708749983044
    },
    "val": {
      "loss": 1.2338095226287842,
      "acc": 0.4159999945163727,
      "macro_f1": 0.41324458831692484,
      "routing_entropy": 3.0127975940704346
    },
    "test": {
      "loss": 1.222965908050537,
      "acc": 0.47600000238418577,
      "macro_f1": 0.47455457946954455,
      "routing_entropy": 3.0239648818969727
    },
    "expert_usage": {
      "moe_0": {
        "selection_counts": [
          3,
          5,
          2275,
          1870,
          1,
          0,
          1035,
          0,
          0,
          0,
          738,
          3,
          0,
          0,
          1813,
          1631,
          0,
          981,
          112,
          0,
          1444,
          1,
          1803,
          663,
          769,
          1324,
          0,
          2742,
          46,
          0,
          1741,
          3000
        ],
        "fixed_selection_counts": [
          0,
          0,
          0,
          0,
          0,
          0,
          0,
          0,
          0,
          0,
          0,
          0,
          0,
          0,
          0,
          0,
          0,
          0,
          0,
          0,
          0,
          0,
          0,
          0,
          0,
          0,
          0,
          0,
          0,
          0,
          0,
          3000
        ],
        "dynamic_selection_counts": [
          3,
          5,
          2275,
          1870,
          1,
          0,
          1035,
          0,
          0,
          0,
          738,
          3,
          0,
          0,
          1813,
          1631,
          0,
          981,
          112,
          0,
          1444,
          1,
          1803,
          663,
          769,
          1324,
          0,
          2742,
          46,
          0,
          1741,
          0
        ]
      }
    }
  },
  {
    "epoch": 6,
    "train": {
      "loss": 1.1447731039259168,
      "acc": 0.48355555571450126,
      "macro_f1": 0.4673684103496557,
      "routing_entropy": 3.022941072781881
    },
    "val": {
      "loss": 1.253314552307129,
      "acc": 0.4799999823570251,
      "macro_f1": 0.4570972432572976,
      "routing_entropy": 2.884432077407837
    },
    "test": {
      "loss": 1.2809757957458496,
      "acc": 0.4399999976158142,
      "macro_f1": 0.4101326783583869,
      "routing_entropy": 2.9008283019065857
    },
    "expert_usage": {
      "moe_0": {
        "selection_counts": [
          86,
          70,
          2197,
          2117,
          1,
          0,
          1099,
          0,
          0,
          0,
          867,
          2,
          0,
          0,
          1909,
          1715,
          0,
          873,
          88,
          33,
          800,
          0,
          1695,
          608,
          802,
          1309,
          0,
          2593,
          424,
          0,
          1712,
          3000
        ],
        "fixed_selection_counts": [
          0,
          0,
          0,
          0,
          0,
          0,
          0,
          0,
          0,
          0,
          0,
          0,
          0,
          0,
          0,
          0,
          0,
          0,
          0,
          0,
          0,
          0,
          0,
          0,
          0,
          0,
          0,
          0,
          0,
          0,
          0,
          3000
        ],
        "dynamic_selection_counts": [
          86,
          70,
          2197,
          2117,
          1,
          0,
          1099,
          0,
          0,
          0,
          867,
          2,
          0,
          0,
          1909,
          1715,
          0,
          873,
          88,
          33,
          800,
          0,
          1695,
          608,
          802,
          1309,
          0,
          2593,
          424,
          0,
          1712,
          0
        ]
      }
    }
  },
  {
    "epoch": 7,
    "train": {
      "loss": 1.1357557197146946,
      "acc": 0.49333333333333335,
      "macro_f1": 0.47773904552155777,
      "routing_entropy": 2.9971733623080783
    },
    "val": {
      "loss": 1.2089302358627319,
      "acc": 0.45199998235702515,
      "macro_f1": 0.41890798939022533,
      "routing_entropy": 2.8539350032806396
    },
    "test": {
      "loss": 1.2306435070037842,
      "acc": 0.456,
      "macro_f1": 0.4232139648049042,
      "routing_entropy": 2.8559640049934387
    },
    "expert_usage": {
      "moe_0": {
        "selection_counts": [
          0,
          25,
          2425,
          2235,
          1,
          0,
          1115,
          0,
          0,
          2,
          1153,
          0,
          0,
          0,
          1838,
          1697,
          0,
          1114,
          25,
          111,
          630,
          0,
          1670,
          726,
          667,
          1116,
          0,
          2509,
          6,
          0,
          1935,
          3000
        ],
        "fixed_selection_counts": [
          0,
          0,
          0,
          0,
          0,
          0,
          0,
          0,
          0,
          0,
          0,
          0,
          0,
          0,
          0,
          0,
          0,
          0,
          0,
          0,
          0,
          0,
          0,
          0,
          0,
          0,
          0,
          0,
          0,
          0,
          0,
          3000
        ],
        "dynamic_selection_counts": [
          0,
          25,
          2425,
          2235,
          1,
          0,
          1115,
          0,
          0,
          2,
          1153,
          0,
          0,
          0,
          1838,
          1697,
          0,
          1114,
          25,
          111,
          630,
          0,
          1670,
          726,
          667,
          1116,
          0,
          2509,
          6,
          0,
          1935,
          0
        ]
      }
    }
  },
  {
    "epoch": 8,
    "train": {
      "loss": 1.135451254632738,
      "acc": 0.4791111119058397,
      "macro_f1": 0.4662656921665054,
      "routing_entropy": 2.946019079950121
    },
    "val": {
      "loss": 1.2605498132705688,
      "acc": 0.43199999141693113,
      "macro_f1": 0.4081227218658549,
      "routing_entropy": 2.8051615953445435
    },
    "test": {
      "loss": 1.2636280097961425,
      "acc": 0.44800000023841857,
      "macro_f1": 0.4155984760095606,
      "routing_entropy": 2.814427673816681
    },
    "expert_usage": {
      "moe_0": {
        "selection_counts": [
          0,
          7,
          2347,
          2308,
          0,
          0,
          1208,
          0,
          0,
          12,
          1120,
          2,
          0,
          4,
          1781,
          1713,
          0,
          1250,
          33,
          0,
          811,
          0,
          1688,
          467,
          671,
          1139,
          0,
          2616,
          0,
          0,
          1823,
          3000
        ],
        "fixed_selection_counts": [
          0,
          0,
          0,
          0,
          0,
          0,
          0,
          0,
          0,
          0,
          0,
          0,
          0,
          0,
          0,
          0,
          0,
          0,
          0,
          0,
          0,
          0,
          0,
          0,
          0,
          0,
          0,
          0,
          0,
          0,
          0,
          3000
        ],
        "dynamic_selection_counts": [
          0,
          7,
          2347,
          2308,
          0,
          0,
          1208,
          0,
          0,
          12,
          1120,
          2,
          0,
          4,
          1781,
          1713,
          0,
          1250,
          33,
          0,
          811,
          0,
          1688,
          467,
          671,
          1139,
          0,
          2616,
          0,
          0,
          1823,
          0
        ]
      }
    }
  },
  {
    "epoch": 9,
    "train": {
      "loss": 1.141028769493103,
      "acc": 0.48577777812216016,
      "macro_f1": 0.46209173313328566,
      "routing_entropy": 2.904166486528185
    },
    "val": {
      "loss": 1.227218967437744,
      "acc": 0.4279999871253967,
      "macro_f1": 0.38672834301773573,
      "routing_entropy": 2.7395529747009277
    },
    "test": {
      "loss": 1.2465043306350707,
      "acc": 0.4619999978542328,
      "macro_f1": 0.42165853874003956,
      "routing_entropy": 2.7436065077781677
    },
    "expert_usage": {
      "moe_0": {
        "selection_counts": [
          0,
          22,
          2335,
          2472,
          1,
          2,
          1282,
          0,
          0,
          0,
          993,
          6,
          0,
          1,
          1870,
          1687,
          0,
          1214,
          41,
          1,
          985,
          0,
          1682,
          623,
          601,
          1124,
          0,
          2666,
          0,
          1,
          1391,
          3000
        ],
        "fixed_selection_counts": [
          0,
          0,
          0,
          0,
          0,
          0,
          0,
          0,
          0,
          0,
          0,
          0,
          0,
          0,
          0,
          0,
          0,
          0,
          0,
          0,
          0,
          0,
          0,
          0,
          0,
          0,
          0,
          0,
          0,
          0,
          0,
          3000
        ],
        "dynamic_selection_counts": [
          0,
          22,
          2335,
          2472,
          1,
          2,
          1282,
          0,
          0,
          0,
          993,
          6,
          0,
          1,
          1870,
          1687,
          0,
          1214,
          41,
          1,
          985,
          0,
          1682,
          623,
          601,
          1124,
          0,
          2666,
          0,
          1,
          1391,
          0
        ]
      }
    }
  },
  {
    "epoch": 10,
    "train": {
      "loss": 1.112795356326633,
      "acc": 0.5022222228315142,
      "macro_f1": 0.4851905571852261,
      "routing_entropy": 2.888366288608975
    },
    "val": {
      "loss": 1.22939684009552,
      "acc": 0.44799998617172243,
      "macro_f1": 0.44128503986760537,
      "routing_entropy": 2.803983688354492
    },
    "test": {
      "loss": 1.2309881258010864,
      "acc": 0.47199999523162844,
      "macro_f1": 0.4651035243572118,
      "routing_entropy": 2.8043880462646484
    },
    "expert_usage": {
      "moe_0": {
        "selection_counts": [
          0,
          7,
          2214,
          2360,
          9,
          0,
          1112,
          0,
          0,
          0,
          1057,
          0,
          0,
          1,
          1901,
          1699,
          0,
          1183,
          57,
          0,
          884,
          0,
          1753,
          740,
          651,
          1083,
          1,
          2833,
          0,
          0,
          1455,
          3000
        ],
        "fixed_selection_counts": [
          0,
          0,
          0,
          0,
          0,
          0,
          0,
          0,
          0,
          0,
          0,
          0,
          0,
          0,
          0,
          0,
          0,
          0,
          0,
          0,
          0,
          0,
          0,
          0,
          0,
          0,
          0,
          0,
          0,
          0,
          0,
          3000
        ],
        "dynamic_selection_counts": [
          0,
          7,
          2214,
          2360,
          9,
          0,
          1112,
          0,
          0,
          0,
          1057,
          0,
          0,
          1,
          1901,
          1699,
          0,
          1183,
          57,
          0,
          884,
          0,
          1753,
          740,
          651,
          1083,
          1,
          2833,
          0,
          0,
          1455,
          0
        ]
      }
    }
  }
]