{
  "run_id": "ref_trees_E16_K4_s1",
  "task_name": "trees",
  "mode": "ref_dynamic",
  "seed": 1,
  "num_experts": 16,
  "top_k": 4,
  "fixed_k": 0,
  "dynamic_k": 4,
  "stats_window_epochs": 3,
  "total_epochs": 10,
  "window_epoch_indices": [
    8,
    9,
    10
  ],
  "layers": {
    "moe_0": {
      "window_sum_counts": [
        0,
        0,
        0,
        3276,
        4626,
        1986,
        7667,
        3363,
        0,
        1952,
        0,
        1642,
        0,
        5474,
        6014,
        0
      ],
      "window_mean_counts": [
        0.0,
        0.0,
        0.0,
        1092.0,
        1542.0,
        662.0,
        2555.6666666666665,
        1121.0,
        0.0,
        650.6666666666666,
        0.0,
        547.3333333333334,
        0.0,
        1824.6666666666667,
        2004.6666666666667,
        0.0
      ],
      "normalized_freq": [
        0.0,
        0.0,
        0.0,
        0.091,
        0.1285,
        0.05516666666666667,
        0.21297222222222223,
        0.09341666666666666,
        0.0,
        0.05422222222222222,
        0.0,
        0.04561111111111111,
        0.0,
        0.15205555555555555,
        0.16705555555555557,
        0.0
      ],
      "ranked_experts": [
        6,
        14,
        13,
        4,
        7,
        3,
        5,
        9,
        11,
        0,
        1,
        2,
        8,
        10,
        12,
        15
      ],
      "top_f_lookup": {
        "1": [
          6
        ],
        "2": [
          6,
          14
        ],
        "3": [
          6,
          14,
          13
        ],
        "4": [
          6,
          14,
          13,
          4
        ],
        "6": [
          6,
          14,
          13,
          4,
          7,
          3
        ],
        "8": [
          6,
          14,
          13,
          4,
          7,
          3,
          5,
          9
        ]
      }
    }
  }
}