[
  {
    "epoch": 1,
    "train": {
      "loss": 1.291352607091268,
      "acc": 0.4502222228580051,
      "macro_f1": 0.44521289580659007,
      "routing_entropy": 3.301596336894565
    },
    "val": {
      "loss": 1.2152141704559327,
      "acc": 0.4919999885559082,
      "macro_f1": 0.4656618641061884,
      "routing_entropy": 3.2441736459732056
    },
    "test": {
      "loss": 1.2107972640991211,
      "acc": 0.5100000014305115,
      "macro_f1": 0.4969767746910606,
      "routing_entropy": 3.215166747570038
    },
    "expert_usage": {
      "moe_0": {
        "selection_counts": [
          789,
          24,
          7,
          14,
          25,
          424,
          106,
          18,
          162,
          1265,
          946,
          5,
          9,
          1,
          1803,
          86,
          717,
          204,
          40,
          457,
          12,
          1,
          83,
          1962,
          892,
          1132,
          1,
          1790,
          500,
          773,
          1515,
          2237
        ],
        "fixed_selection_counts": [
          0,
          0,
          0,
          0,
          0,
          0,
          0,
          0,
          0,
          0,
          0,
          0,
          0,
          0,
          0,
          0,
          0,
          0,
          0,
          0,
          0,
          0,
          0,
          0,
          0,
          0,
          0,
          0,
          0,
          0,
          0,
          0
        ],
        "dynamic_selection_counts": [
          789,
          24,
          7,
          14,
          25,
          424,
          106,
          18,
          162,
          1265,
          946,
          5,
          9,
          1,
          1803,
          86,
          717,
          204,
          40,
          457,
          12,
          1,
          83,
          1962,
          892,
          1132,
          1,
          1790,
          500,
          773,
          1515,
          2237
        ]
      }
    }
  },
  {
    "epoch": 2,
    "train": {
      "loss": 1.1401196965111626,
      "acc": 0.5439999997350905,
      "macro_f1": 0.5403196244075459,
      "routing_entropy": 3.134861866633097
    },
    "val": {
      "loss": 1.1774884290695191,
      "acc": 0.5759999845027923,
      "macro_f1": 0.5600671201460715,
      "routing_entropy": 3.0070828199386597
    },
    "test": {
      "loss": 1.2382327089309693,
      "acc": 0.5279999990463257,
      "macro_f1": 0.5154786955866811,
      "routing_entropy": 3.006866157054901
    },
    "expert_usage": {
      "moe_0": {
        "selection_counts": [
          557,
          9,
          0,
          0,
          0,
          417,
          0,
          0,
          119,
          1390,
          977,
          0,
          1,
          0,
          1905,
          0,
          840,
          6,
          0,
          497,
          0,
          0,
          0,
          2172,
          771,
          1261,
          0,
          1577,
          772,
          561,
          1553,
          2615
        ],
        "fixed_selection_counts": [
          0,
          0,
          0,
          0,
          0,
          0,
          0,
          0,
          0,
          0,
          0,
          0,
          0,
          0,
          0,
          0,
          0,
          0,
          0,
          0,
          0,
          0,
          0,
          0,
          0,
          0,
          0,
          0,
          0,
          0,
          0,
          0
        ],
        "dynamic_selection_counts": [
          557,
          9,
          0,
          0,
          0,
          417,
          0,
          0,
          119,
          1390,
          977,
          0,
          1,
          0,
          1905,
          0,
          840,
          6,
          0,
          497,
          0,
          0,
          0,
          2172,
          771,
          1261,
          0,
          1577,
          772,
          561,
          1553,
          2615
        ]
      }
    }
  },
  {
    "epoch": 3,
    "train": {
      "loss": 1.083063308927748,
      "acc": 0.5702222224871317,
      "macro_f1": 0.5680109335624238,
      "routing_entropy": 3.102016554938422
    },
    "val": {
      "loss": 1.0848220701217652,
      "acc": 0.5759999849796296,
      "macro_f1": 0.560693158067731,
      "routing_entropy": 2.9493764638900757
    },
    "test": {
      "loss": 1.1094105739593505,
      "acc": 0.5619999990463257,
      "macro_f1": 0.553214079120545,
      "routing_entropy": 2.94888573884964
    },
    "expert_usage": {
      "moe_0": {
        "selection_counts": [
          654,
          4,
          0,
          1,
          0,
          281,
          0,
          0,
          4,
          1386,
          891,
          0,
          2,
          0,
          2285,
          1,
          816,
          0,
          0,
          362,
          0,
          0,
          2,
          2034,
          885,
          1747,
          0,
          1520,
          633,
          182,
          1567,
          2743
        ],
        "fixed_selection_counts": [
          0,
          0,
          0,
          0,
          0,
          0,
          0,
          0,
          0,
          0,
          0,
          0,
          0,
          0,
          0,
          0,
          0,
          0,
          0,
          0,
          0,
          0,
          0,
          0,
          0,
          0,
          0,
          0,
          0,
          0,
          0,
          0
        ],
        "dynamic_selection_counts": [
          654,
          4,
          0,
          1,
          0,
          281,
          0,
          0,
          4,
          1386,
          891,
          0,
          2,
          0,
          2285,
          1,
          816,
          0,
          0,
          362,
          0,
          0,
          2,
          2034,
          885,
          1747,
          0,
          1520,
          633,
          182,
          1567,
          2743
        ]
      }
    }
  },
  {
    "epoch": 4,
    "train": {
      "loss": 1.0733514507081774,
      "acc": 0.5680000009006924,
      "macro_f1": 0.5667731374103754,
      "routing_entropy": 3.0275950166914196
    },
    "val": {
      "loss": 1.0281993026733398,
      "acc": 0.6279999766349792,
      "macro_f1": 0.6245290223699331,
      "routing_entropy": 2.9396647214889526
    },
    "test": {
      "loss": 1.0595490465164183,
      "acc": 0.574000006198883,
      "macro_f1": 0.5704357657449451,
      "routing_entropy": 2.913481831550598
    },
    "expert_usage": {
      "moe_0": {
        "selection_counts": [
          791,
          0,
          0,
          1,
          0,
          393,
          0,
          0,
          5,
          1467,
          849,
          0,
          22,
          0,
          1811,
          0,
          742,
          0,
          0,
          426,
          1,
          0,
          2,
          2092,
          961,
          1812,
          0,
          1511,
          819,
          81,
          1297,
          2917
        ],
        "fixed_selection_counts": [
          0,
          0,
          0,
          0,
          0,
          0,
          0,
          0,
          0,
          0,
          0,
          0,
          0,
          0,
          0,
          0,
          0,
          0,
          0,
          0,
          0,
          0,
          0,
          0,
          0,
          0,
          0,
          0,
          0,
          0,
          0,
          0
        ],
        "dynamic_selection_counts": [
          791,
          0,
          0,
          1,
          0,
          393,
          0,
          0,
          5,
          1467,
          849,
          0,
          22,
          0,
          1811,
          0,
          742,
          0,
          0,
          426,
          1,
          0,
          2,
          2092,
          961,
          1812,
          0,
          1511,
          819,
          81,
          1297,
          2917
        ]
      }
    }
  },
  {
    "epoch": 5,
    "train": {
      "loss": 1.0288376829359267,
      "acc": 0.6088888900544909,
      "macro_f1": 0.6074137715706396,
      "routing_entropy": 3.020622134208679
    },
    "val": {
      "loss": 0.9768244819641113,
      "acc": 0.6359999713897705,
      "macro_f1": 0.6300778446405022,
      "routing_entropy": 2.890276074409485
    },
    "test": {
      "loss": 1.039034236907959,
      "acc": 0.5859999942779541,
      "macro_f1": 0.5850346470391796,
      "routing_entropy": 2.894597113132477
    },
    "expert_usage": {
      "moe_0": {
        "selection_counts": [
          459,
          0,
          0,
          0,
          0,
          439,
          0,
          0,
          8,
          1553,
          1031,
          0,
          0,
          0,
          1815,
          0,
          618,
          3,
          0,
          515,
          3,
          0,
          2,
          2030,
          988,
          1646,
          0,
          1442,
          1099,
          159,
          1387,
          2803
        ],
        "fixed_selection_counts": [
          0,
          0,
          0,
          0,
          0,
          0,
          0,
          0,
          0,
          0,
          0,
          0,
          0,
          0,
          0,
          0,
          0,
          0,
          0,
          0,
          0,
          0,
          0,
          0,
          0,
          0,
          0,
          0,
          0,
          0,
          0,
          0
        ],
        "dynamic_selection_counts": [
          459,
          0,
          0,
          0,
          0,
          439,
          0,
          0,
          8,
          1553,
          1031,
          0,
          0,
          0,
          1815,
          0,
          618,
          3,
          0,
          515,
          3,
          0,
          2,
          2030,
          988,
          1646,
          0,
          1442,
          1099,
          159,
          1387,
          2803
        ]
      }
    }
  },
  {
    "epoch": 6,
    "train": {
      "loss": 0.9776596349080403,
      "acc": 0.633777778784434,
      "macro_f1": 0.6332493769849654,
      "routing_entropy": 3.020004471143087
    },
    "val": {
      "loss": 0.9986062269210816,
      "acc": 0.599999990940094,
      "macro_f1": 0.5946340765752292,
      "routing_entropy": 2.994110584259033
    },
    "test": {
      "loss": 0.981440435409546,
      "acc": 0.6199999961853028,
      "macro_f1": 0.6155013090001111,
      "routing_entropy": 2.960680067539215
    },
    "expert_usage": {
      "moe_0": {
        "selection_counts": [
          663,
          0,
          0,
          0,
          0,
          497,
          0,
          0,
          9,
          1611,
          1152,
          0,
          0,
          0,
          2027,
          0,
          658,
          3,
          0,
          505,
          0,
          0,
          1,
          1649,
          961,
          1783,
          0,
          1469,
          767,
          210,
          1311,
          2724
        ],
        "fixed_selection_counts": [
          0,
          0,
          0,
          0,
          0,
          0,
          0,
          0,
          0,
          0,
          0,
          0,
          0,
          0,
          0,
          0,
          0,
          0,
          0,
          0,
          0,
          0,
          0,
          0,
          0,
          0,
          0,
          0,
          0,
          0,
          0,
          0
        ],
        "dynamic_selection_counts": [
          663,
          0,
          0,
          0,
          0,
          497,
          0,
          0,
          9,
          1611,
          1152,
          0,
          0,
          0,
          2027,
          0,
          658,
          3,
          0,
          505,
          0,
          0,
          1,
          1649,
          961,
          1783,
          0,
          1469,
          767,
          210,
          1311,
          2724
        ]
      }
    }
  },
  {
    "epoch": 7,
    "train": {
      "loss": 0.9471025838851929,
      "acc": 0.6364444454511007,
      "macro_f1": 0.6352488331005361,
      "routing_entropy": 3.0163123077816434
    },
    "val": {
      "loss": 0.9806805019378662,
      "acc": 0.631999990940094,
      "macro_f1": 0.6310887729781739,
      "routing_entropy": 2.8465771675109863
    },
    "test": {
      "loss": 1.0020312776565552,
      "acc": 0.5940000009536743,
      "macro_f1": 0.5954653151745173,
      "routing_entropy": 2.806848883628845
    },
    "expert_usage": {
      "moe_0": {
        "selection_counts": [
          458,
          1,
          0,
          0,
          0,
          571,
          0,
          0,
          13,
          1412,
          966,
          0,
          0,
          0,
          1992,
          0,
          529,
          12,
          0,
          503,
          0,
          0,
          0,
          1780,
          1073,
          1702,
          0,
          1506,
          951,
          162,
          1562,
          2807
        ],
        "fixed_selection_counts": [
          0,
          0,
          0,
          0,
          0,
          0,
          0,
          0,
          0,
          0,
          0,
          0,
          0,
          0,
          0,
          0,
          0,
          0,
          0,
          0,
          0,
          0,
          0,
          0,
          0,
          0,
          0,
          0,
          0,
          0,
          0,
          0
        ],
        "dynamic_selection_counts": [
          458,
          1,
          0,
          0,
          0,
          571,
          0,
          0,
          13,
          1412,
          966,
          0,
          0,
          0,
          1992,
          0,
          529,
          12,
          0,
          503,
          0,
          0,
          0,
          1780,
          1073,
          1702,
          0,
          1506,
          951,
          162,
          1562,
          2807
        ]
      }
    }
  },
  {
    "epoch": 8,
    "train": {
      "loss": 0.9571793950928582,
      "acc": 0.6386666663487752,
      "macro_f1": 0.6371464210272968,
      "routing_entropy": 3.0084589454862805
    },
    "val": {
      "loss": 0.9676291637420654,
      "acc": 0.6239999902248382,
      "macro_f1": 0.6150516007828392,
      "routing_entropy": 2.917960047721863
    },
    "test": {
      "loss": 0.9798265891075134,
      "acc": 0.6120000009536744,
      "macro_f1": 0.6019578493589383,
      "routing_entropy": 2.9047603607177734
    },
    "expert_usage": {
      "moe_0": {
        "selection_counts": [
          392,
          0,
          0,
          0,
          0,
          557,
          0,
          0,
          6,
          1454,
          1187,
          0,
          0,
          0,
          2139,
          0,
          256,
          62,
          0,
          490,
          0,
          0,
          0,
          1830,
          1177,
          1606,
          1,
          1488,
          1034,
          130,
          1527,
          2664
        ],
        "fixed_selection_counts": [
          0,
          0,
          0,
          0,
          0,
          0,
          0,
          0,
          0,
          0,
          0,
          0,
          0,
          0,
          0,
          0,
          0,
          0,
          0,
          0,
          0,
          0,
          0,
          0,
          0,
          0,
          0,
          0,
          0,
          0,
          0,
          0
        ],
        "dynamic_selection_counts": [
          392,
          0,
          0,
          0,
          0,
          557,
          0,
          0,
          6,
          1454,
          1187,
          0,
          0,
          0,
          2139,
          0,
          256,
          62,
          0,
          490,
          0,
          0,
          0,
          1830,
          1177,
          1606,
          1,
          1488,
          1034,
          130,
          1527,
          2664
        ]
      }
    }
  },
  {
    "epoch": 9,
    "train": {
      "loss": 0.9086512862311469,
      "acc": 0.6577777784135607,
      "macro_f1": 0.6576531947634594,
      "routing_entropy": 2.982554223802355
    },
    "val": {
      "loss": 1.031459732055664,
      "acc": 0.6159999766349793,
      "macro_f1": 0.6063396817043578,
      "routing_entropy": 2.7959303855895996
    },
    "test": {
      "loss": 0.992587899684906,
      "acc": 0.5920000033378601,
      "macro_f1": 0.5903372129620902,
      "routing_entropy": 2.7531147599220276
    },
    "expert_usage": {
      "moe_0": {
        "selection_counts": [
          449,
          0,
          0,
          0,
          0,
          652,
          0,
          0,
          0,
          1633,
          1079,
          0,
          0,
          0,
          2059,
          0,
          373,
          0,
          0,
          572,
          0,
          0,
          0,
          1779,
          1114,
          1634,
          0,
          1564,
          849,
          164,
          1328,
          2751
        ],
        "fixed_selection_counts": [
          0,
          0,
          0,
          0,
          0,
          0,
          0,
          0,
          0,
          0,
          0,
          0,
          0,
          0,
          0,
          0,
          0,
          0,
          0,
          0,
          0,
          0,
          0,
          0,
          0,
          0,
          0,
          0,
          0,
          0,
          0,
          0
        ],
        "dynamic_selection_counts": [
          449,
          0,
          0,
          0,
          0,
          652,
          0,
          0,
          0,
          1633,
          1079,
          0,
          0,
          0,
          2059,
          0,
          373,
          0,
          0,
          572,
          0,
          0,
          0,
          1779,
          1114,
          1634,
          0,
          1564,
          849,
          164,
          1328,
          2751
        ]
      }
    }
  },
  {
    "epoch": 10,
    "train": {
      "loss": 0.8732831277317471,
      "acc": 0.6711111124886406,
      "macro_f1": 0.6701213220449727,
      "routing_entropy": 2.9429743422402277
    },
    "val": {
      "loss": 0.9733894147872925,
      "acc": 0.6399999871253967,
      "macro_f1": 0.6410246121064126,
      "routing_entropy": 2.903789758682251
    },
    "test": {
      "loss": 0.9519924831390381,
      "acc": 0.6159999985694885,
      "macro_f1": 0.6179670491990737,
      "routing_entropy": 2.8578023314476013
    },
    "expert_usage": {
      "moe_0": {
        "selection_counts": [
          578,
          0,
          16,
          0,
          0,
          625,
          0,
          0,
          0,
          1564,
          941,
          0,
          0,
          0,
          2093,
          2,
          271,
          0,
          0,
          575,
          0,
          0,
          0,
          1904,
          1177,
          1638,
          0,
          1604,
          643,
          237,
          1269,
          2863
        ],
        "fixed_selection_counts": [
          0,
          0,
          0,
          0,
          0,
          0,
          0,
          0,
          0,
          0,
          0,
          0,
          0,
          0,
          0,
          0,
          0,
          0,
          0,
          0,
          0,
          0,
          0,
          0,
          0,
          0,
          0,
          0,
          0,
          0,
          0,
          0
        ],
        "dynamic_selection_counts": [
          578,
          0,
          16,
          0,
          0,
          625,
          0,
          0,
          0,
          1564,
          941,
          0,
          0,
          0,
          2093,
          2,
          271,
          0,
          0,
          575,
          0,
          0,
          0,
          1904,
          1177,
          1638,
          0,
          1604,
          643,
          237,
          1269,
          2863
        ]
      }
    }
  }
]