[
  {
    "epoch": 1,
    "train": {
      "loss": 1.474361658944024,
      "acc": 0.3520000001589457,
      "macro_f1": 0.33277631295743343,
      "routing_entropy": 2.6669006612565784
    },
    "val": {
      "loss": 1.4614303579330445,
      "acc": 0.3199999930858612,
      "macro_f1": 0.28404290004290006,
      "routing_entropy": 2.6028586626052856
    },
    "test": {
      "loss": 1.426948945045471,
      "acc": 0.41199999856948855,
      "macro_f1": 0.3910406932117593,
      "routing_entropy": 2.6112760305404663
    },
    "expert_usage": {
      "moe_0": {
        "selection_counts": [
          991,
          1038,
          1562,
          315,
          139,
          801,
          3000,
          1787,
          2204,
          1149,
          1453,
          121,
          1195,
          1306,
          749,
          190
        ],
        "fixed_selection_counts": [
          0,
          0,
          0,
          0,
          0,
          0,
          3000,
          0,
          0,
          0,
          0,
          0,
          0,
          0,
          0,
          0
        ],
        "dynamic_selection_counts": [
          991,
          1038,
          1562,
          315,
          139,
          801,
          0,
          1787,
          2204,
          1149,
          1453,
          121,
          1195,
          1306,
          749,
          190
        ]
      }
    }
  },
  {
    "epoch": 2,
    "train": {
      "loss": 1.3722877379523384,
      "acc": 0.4093333339426253,
      "macro_f1": 0.4009586908986581,
      "routing_entropy": 2.5645717514885797
    },
    "val": {
      "loss": 1.4799234390258789,
      "acc": 0.35599998927116394,
      "macro_f1": 0.31897807099327424,
      "routing_entropy": 2.476988196372986
    },
    "test": {
      "loss": 1.4503107872009278,
      "acc": 0.3920000009536743,
      "macro_f1": 0.36984912113058566,
      "routing_entropy": 2.4908377528190613
    },
    "expert_usage": {
      "moe_0": {
        "selection_counts": [
          1707,
          1018,
          2431,
          0,
          0,
          133,
          3000,
          2174,
          1863,
          823,
          1500,
          2,
          1079,
          1570,
          699,
          1
        ],
        "fixed_selection_counts": [
          0,
          0,
          0,
          0,
          0,
          0,
          3000,
          0,
          0,
          0,
          0,
          0,
          0,
          0,
          0,
          0
        ],
        "dynamic_selection_counts": [
          1707,
          1018,
          2431,
          0,
          0,
          133,
          0,
          2174,
          1863,
          823,
          1500,
          2,
          1079,
          1570,
          699,
          1
        ]
      }
    }
  },
  {
    "epoch": 3,
    "train": {
      "loss": 1.3542485486136542,
      "acc": 0.41555555579397413,
      "macro_f1": 0.4071525019496118,
      "routing_entropy": 2.5280774964226618
    },
    "val": {
      "loss": 1.3847090091705323,
      "acc": 0.3679999842643738,
      "macro_f1": 0.37472540018700506,
      "routing_entropy": 2.481325626373291
    },
    "test": {
      "loss": 1.3878104925155639,
      "acc": 0.4140000011920929,
      "macro_f1": 0.4155700714321404,
      "routing_entropy": 2.4948633313179016
    },
    "expert_usage": {
      "moe_0": {
        "selection_counts": [
          1872,
          1172,
          2502,
          0,
          0,
          168,
          3000,
          2211,
          1849,
          795,
          1705,
          1,
          569,
          1548,
          597,
          11
        ],
        "fixed_selection_counts": [
          0,
          0,
          0,
          0,
          0,
          0,
          3000,
          0,
          0,
          0,
          0,
          0,
          0,
          0,
          0,
          0
        ],
        "dynamic_selection_counts": [
          1872,
          1172,
          2502,
          0,
          0,
          168,
          0,
          2211,
          1849,
          795,
          1705,
          1,
          569,
          1548,
          597,
          11
        ]
      }
    }
  },
  {
    "epoch": 4,
    "train": {
      "loss": 1.2960652044084338,
      "acc": 0.45866666719648574,
      "macro_f1": 0.4522789127357262,
      "routing_entropy": 2.5195898479885526
    },
    "val": {
      "loss": 1.3468241205215454,
      "acc": 0.42399999022483825,
      "macro_f1": 0.41486231162120485,
      "routing_entropy": 2.436544179916382
    },
    "test": {
      "loss": 1.3530334558486938,
      "acc": 0.436000002861023,
      "macro_f1": 0.42744087353211613,
      "routing_entropy": 2.4424357414245605
    },
    "expert_usage": {
      "moe_0": {
        "selection_counts": [
          1716,
          1192,
          2326,
          2,
          1,
          369,
          3000,
          2149,
          1782,
          1234,
          1519,
          8,
          554,
          1500,
          633,
          15
        ],
        "fixed_selection_counts": [
          0,
          0,
          0,
          0,
          0,
          0,
          3000,
          0,
          0,
          0,
          0,
          0,
          0,
          0,
          0,
          0
        ],
        "dynamic_selection_counts": [
          1716,
          1192,
          2326,
          2,
          1,
          369,
          0,
          2149,
          1782,
          1234,
          1519,
          8,
          554,
          1500,
          633,
          15
        ]
      }
    }
  },
  {
    "epoch": 5,
    "train": {
      "loss": 1.289309535238478,
      "acc": 0.45733333394262526,
      "macro_f1": 0.448998695952558,
      "routing_entropy": 2.4766081439124212
    },
    "val": {
      "loss": 1.439929811477661,
      "acc": 0.3359999842643738,
      "macro_f1": 0.32366209586066674,
      "routing_entropy": 2.3952598571777344
    },
    "test": {
      "loss": 1.3784635848999023,
      "acc": 0.41399999856948855,
      "macro_f1": 0.41262186988218386,
      "routing_entropy": 2.399664282798767
    },
    "expert_usage": {
      "moe_0": {
        "selection_counts": [
          1620,
          1511,
          2108,
          1,
          1,
          232,
          3000,
          2006,
          1800,
          1203,
          1689,
          13,
          606,
          1550,
          660,
          0
        ],
        "fixed_selection_counts": [
          0,
          0,
          0,
          0,
          0,
          0,
          3000,
          0,
          0,
          0,
          0,
          0,
          0,
          0,
          0,
          0
        ],
        "dynamic_selection_counts": [
          1620,
          1511,
          2108,
          1,
          1,
          232,
          0,
          2006,
          1800,
          1203,
          1689,
          13,
          606,
          1550,
          660,
          0
        ]
      }
    }
  },
  {
    "epoch": 6,
    "train": {
      "loss": 1.257001105202569,
      "acc": 0.47822222169240314,
      "macro_f1": 0.47620208545273657,
      "routing_entropy": 2.459674517313639
    },
    "val": {
      "loss": 1.4674481058120727,
      "acc": 0.3759999854564667,
      "macro_f1": 0.3451939624902855,
      "routing_entropy": 2.318487524986267
    },
    "test": {
      "loss": 1.4773072853088378,
      "acc": 0.4259999978542328,
      "macro_f1": 0.41316906422885646,
      "routing_entropy": 2.334355592727661
    },
    "expert_usage": {
      "moe_0": {
        "selection_counts": [
          1479,
          1227,
          2274,
          0,
          0,
          344,
          3000,
          2051,
          1657,
          1268,
          1682,
          82,
          709,
          1625,
          602,
          0
        ],
        "fixed_selection_counts": [
          0,
          0,
          0,
          0,
          0,
          0,
          3000,
          0,
          0,
          0,
          0,
          0,
          0,
          0,
          0,
          0
        ],
        "dynamic_selection_counts": [
          1479,
          1227,
          2274,
          0,
          0,
          344,
          0,
          2051,
          1657,
          1268,
          1682,
          82,
          709,
          1625,
          602,
          0
        ]
      }
    }
  },
  {
    "epoch": 7,
    "train": {
      "loss": 1.2157938735749987,
      "acc": 0.4951111114554935,
      "macro_f1": 0.48676199816309146,
      "routing_entropy": 2.4346065123875937
    },
    "val": {
      "loss": 1.394526864051819,
      "acc": 0.41999999451637265,
      "macro_f1": 0.4275726794458092,
      "routing_entropy": 2.3749457597732544
    },
    "test": {
      "loss": 1.3635109243392944,
      "acc": 0.4239999985694885,
      "macro_f1": 0.42742964248028226,
      "routing_entropy": 2.3929267525672913
    },
    "expert_usage": {
      "moe_0": {
        "selection_counts": [
          1576,
          1340,
          2431,
          2,
          3,
          364,
          3000,
          1936,
          1767,
          1277,
          1501,
          61,
          798,
          1331,
          613,
          0
        ],
        "fixed_selection_counts": [
          0,
          0,
          0,
          0,
          0,
          0,
          3000,
          0,
          0,
          0,
          0,
          0,
          0,
          0,
          0,
          0
        ],
        "dynamic_selection_counts": [
          1576,
          1340,
          2431,
          2,
          3,
          364,
          0,
          1936,
          1767,
          1277,
          1501,
          61,
          798,
          1331,
          613,
          0
        ]
      }
    }
  },
  {
    "epoch": 8,
    "train": {
      "loss": 1.2037713627285427,
      "acc": 0.4951111116409302,
      "macro_f1": 0.49222298283049015,
      "routing_entropy": 2.4224489529927573
    },
    "val": {
      "loss": 1.4997093467712401,
      "acc": 0.4399999845027924,
      "macro_f1": 0.44105205764372457,
      "routing_entropy": 2.2967387437820435
    },
    "test": {
      "loss": 1.4394502048492432,
      "acc": 0.44800000071525575,
      "macro_f1": 0.437548298020765,
      "routing_entropy": 2.307294547557831
    },
    "expert_usage": {
      "moe_0": {
        "selection_counts": [
          1426,
          1401,
          2001,
          0,
          4,
          397,
          3000,
          2019,
          1829,
          1155,
          1560,
          35,
          789,
          1621,
          763,
          0
        ],
        "fixed_selection_counts": [
          0,
          0,
          0,
          0,
          0,
          0,
          3000,
          0,
          0,
          0,
          0,
          0,
          0,
          0,
          0,
          0
        ],
        "dynamic_selection_counts": [
          1426,
          1401,
          2001,
          0,
          4,
          397,
          0,
          2019,
          1829,
          1155,
          1560,
          35,
          789,
          1621,
          763,
          0
        ]
      }
    }
  },
  {
    "epoch": 9,
    "train": {
      "loss": 1.1965430369906955,
      "acc": 0.5124444445504083,
      "macro_f1": 0.5097916525354859,
      "routing_entropy": 2.420379016134474
    },
    "val": {
      "loss": 1.3297695121765136,
      "acc": 0.42399999451637266,
      "macro_f1": 0.4271986327338439,
      "routing_entropy": 2.3969141244888306
    },
    "test": {
      "loss": 1.284001329421997,
      "acc": 0.46600000286102294,
      "macro_f1": 0.46085754179255617,
      "routing_entropy": 2.4037370681762695
    },
    "expert_usage": {
      "moe_0": {
        "selection_counts": [
          1458,
          1243,
          2271,
          1,
          1,
          492,
          3000,
          2121,
          1767,
          1087,
          1489,
          20,
          763,
          1509,
          778,
          0
        ],
        "fixed_selection_counts": [
          0,
          0,
          0,
          0,
          0,
          0,
          3000,
          0,
          0,
          0,
          0,
          0,
          0,
          0,
          0,
          0
        ],
        "dynamic_selection_counts": [
          1458,
          1243,
          2271,
          1,
          1,
          492,
          0,
          2121,
          1767,
          1087,
          1489,
          20,
          763,
          1509,
          778,
          0
        ]
      }
    }
  },
  {
    "epoch": 10,
    "train": {
      "loss": 1.163795104238722,
      "acc": 0.5213333333333333,
      "macro_f1": 0.5168704176903793,
      "routing_entropy": 2.4250586695141263
    },
    "val": {
      "loss": 1.2642265605926513,
      "acc": 0.47199999046325686,
      "macro_f1": 0.467783158261361,
      "routing_entropy": 2.338266372680664
    },
    "test": {
      "loss": 1.3262245864868165,
      "acc": 0.4880000023841858,
      "macro_f1": 0.4810752736364751,
      "routing_entropy": 2.3468207716941833
    },
    "expert_usage": {
      "moe_0": {
        "selection_counts": [
          1454,
          1476,
          2370,
          0,
          13,
          896,
          3000,
          1939,
          1813,
          1253,
          1355,
          27,
          339,
          1298,
          767,
          0
        ],
        "fixed_selection_counts": [
          0,
          0,
          0,
          0,
          0,
          0,
          3000,
          0,
          0,
          0,
          0,
          0,
          0,
          0,
          0,
          0
        ],
        "dynamic_selection_counts": [
          1454,
          1476,
          2370,
          0,
          13,
          896,
          0,
          1939,
          1813,
          1253,
          1355,
          27,
          339,
          1298,
          767,
          0
        ]
      }
    }
  }
]