{
  "run_id": "hyb_p03_trees_to_flowers_E32_K8_F2_s1",
  "mode": "hybrid_transfer",
  "task_name": "flowers",
  "seed": 1,
  "num_experts": 32,
  "top_k": 8,
  "fixed_k": 2,
  "dynamic_k": 6,
  "epochs": [
    {
      "epoch": 1,
      "layers": {
        "moe_0": {
          "selection_counts": [
            14,
            13,
            91,
            12,
            1344,
            55,
            3000,
            325,
            61,
            1200,
            974,
            990,
            0,
            1,
            2140,
            1145,
            968,
            560,
            92,
            1933,
            1329,
            1187,
            107,
            3000,
            135,
            1362,
            1,
            847,
            8,
            8,
            680,
            418
          ],
          "fixed_selection_counts": [
            0,
            0,
            0,
            0,
            0,
            0,
            3000,
            0,
            0,
            0,
            0,
            0,
            0,
            0,
            0,
            0,
            0,
            0,
            0,
            0,
            0,
            0,
            0,
            3000,
            0,
            0,
            0,
            0,
            0,
            0,
            0,
            0
          ],
          "dynamic_selection_counts": [
            14,
            13,
            91,
            12,
            1344,
            55,
            0,
            325,
            61,
            1200,
            974,
            990,
            0,
            1,
            2140,
            1145,
            968,
            560,
            92,
            1933,
            1329,
            1187,
            107,
            0,
            135,
            1362,
            1,
            847,
            8,
            8,
            680,
            418
          ]
        }
      }
    },
    {
      "epoch": 2,
      "layers": {
        "moe_0": {
          "selection_counts": [
            0,
            0,
            1,
            0,
            1476,
            0,
            3000,
            997,
            0,
            1368,
            1049,
            234,
            78,
            0,
            2372,
            1471,
            1081,
            746,
            5,
            2266,
            1115,
            1262,
            17,
            3000,
            0,
            1511,
            0,
            590,
            1,
            0,
            359,
            1
          ],
          "fixed_selection_counts": [
            0,
            0,
            0,
            0,
            0,
            0,
            3000,
            0,
            0,
            0,
            0,
            0,
            0,
            0,
            0,
            0,
            0,
            0,
            0,
            0,
            0,
            0,
            0,
            3000,
            0,
            0,
            0,
            0,
            0,
            0,
            0,
            0
          ],
          "dynamic_selection_counts": [
            0,
            0,
            1,
            0,
            1476,
            0,
            0,
            997,
            0,
            1368,
            1049,
            234,
            78,
            0,
            2372,
            1471,
            1081,
            746,
            5,
            2266,
            1115,
            1262,
            17,
            0,
            0,
            1511,
            0,
            590,
            1,
            0,
            359,
            1
          ]
        }
      }
    },
    {
      "epoch": 3,
      "layers": {
        "moe_0": {
          "selection_counts": [
            0,
            1,
            0,
            0,
            1452,
            0,
            3000,
            966,
            0,
            1505,
            1091,
            92,
            9,
            0,
            2278,
            1546,
            1287,
            674,
            0,
            2393,
            1055,
            1222,
            0,
            3000,
            0,
            1191,
            1,
            593,
            0,
            0,
            644,
            0
          ],
          "fixed_selection_counts": [
            0,
            0,
            0,
            0,
            0,
            0,
            3000,
            0,
            0,
            0,
            0,
            0,
            0,
            0,
            0,
            0,
            0,
            0,
            0,
            0,
            0,
            0,
            0,
            3000,
            0,
            0,
            0,
            0,
            0,
            0,
            0,
            0
          ],
          "dynamic_selection_counts": [
            0,
            1,
            0,
            0,
            1452,
            0,
            0,
            966,
            0,
            1505,
            1091,
            92,
            9,
            0,
            2278,
            1546,
            1287,
            674,
            0,
            2393,
            1055,
            1222,
            0,
            0,
            0,
            1191,
            1,
            593,
            0,
            0,
            644,
            0
          ]
        }
      }
    },
    {
      "epoch": 4,
      "layers": {
        "moe_0": {
          "selection_counts": [
            0,
            0,
            0,
            0,
            1506,
            0,
            3000,
            1047,
            0,
            1818,
            1237,
            69,
            50,
            0,
            2048,
            1498,
            1048,
            339,
            0,
            2327,
            1723,
            1305,
            0,
            3000,
            0,
            990,
            0,
            700,
            0,
            0,
            295,
            0
          ],
          "fixed_selection_counts": [
            0,
            0,
            0,
            0,
            0,
            0,
            3000,
            0,
            0,
            0,
            0,
            0,
            0,
            0,
            0,
            0,
            0,
            0,
            0,
            0,
            0,
            0,
            0,
            3000,
            0,
            0,
            0,
            0,
            0,
            0,
            0,
            0
          ],
          "dynamic_selection_counts": [
            0,
            0,
            0,
            0,
            1506,
            0,
            0,
            1047,
            0,
            1818,
            1237,
            69,
            50,
            0,
            2048,
            1498,
            1048,
            339,
            0,
            2327,
            1723,
            1305,
            0,
            0,
            0,
            990,
            0,
            700,
            0,
            0,
            295,
            0
          ]
        }
      }
    },
    {
      "epoch": 5,
      "layers": {
        "moe_0": {
          "selection_counts": [
            0,
            0,
            0,
            0,
            1593,
            0,
            3000,
            1307,
            0,
            2142,
            1124,
            68,
            4,
            0,
            2178,
            1515,
            1321,
            230,
            3,
            2134,
            1324,
            1047,
            0,
            3000,
            0,
            1076,
            0,
            879,
            0,
            0,
            54,
            1
          ],
          "fixed_selection_counts": [
            0,
            0,
            0,
            0,
            0,
            0,
            3000,
            0,
            0,
            0,
            0,
            0,
            0,
            0,
            0,
            0,
            0,
            0,
            0,
            0,
            0,
            0,
            0,
            3000,
            0,
            0,
            0,
            0,
            0,
            0,
            0,
            0
          ],
          "dynamic_selection_counts": [
            0,
            0,
            0,
            0,
            1593,
            0,
            0,
            1307,
            0,
            2142,
            1124,
            68,
            4,
            0,
            2178,
            1515,
            1321,
            230,
            3,
            2134,
            1324,
            1047,
            0,
            0,
            0,
            1076,
            0,
            879,
            0,
            0,
            54,
            1
          ]
        }
      }
    },
    {
      "epoch": 6,
      "layers": {
        "moe_0": {
          "selection_counts": [
            0,
            1,
            0,
            0,
            1641,
            54,
            3000,
            1180,
            0,
            2116,
            1190,
            155,
            1,
            0,
            2163,
            1573,
            1338,
            211,
            0,
            2293,
            1424,
            1156,
            1,
            3000,
            0,
            1033,
            0,
            432,
            0,
            1,
            28,
            9
          ],
          "fixed_selection_counts": [
            0,
            0,
            0,
            0,
            0,
            0,
            3000,
            0,
            0,
            0,
            0,
            0,
            0,
            0,
            0,
            0,
            0,
            0,
            0,
            0,
            0,
            0,
            0,
            3000,
            0,
            0,
            0,
            0,
            0,
            0,
            0,
            0
          ],
          "dynamic_selection_counts": [
            0,
            1,
            0,
            0,
            1641,
            54,
            0,
            1180,
            0,
            2116,
            1190,
            155,
            1,
            0,
            2163,
            1573,
            1338,
            211,
            0,
            2293,
            1424,
            1156,
            1,
            0,
            0,
            1033,
            0,
            432,
            0,
            1,
            28,
            9
          ]
        }
      }
    },
    {
      "epoch": 7,
      "layers": {
        "moe_0": {
          "selection_counts": [
            0,
            0,
            0,
            0,
            1565,
            14,
            3000,
            1132,
            0,
            2203,
            1269,
            234,
            0,
            0,
            2040,
            1413,
            1110,
            421,
            39,
            2284,
            1352,
            1237,
            1,
            3000,
            0,
            1119,
            0,
            436,
            0,
            0,
            45,
            86
          ],
          "fixed_selection_counts": [
            0,
            0,
            0,
            0,
            0,
            0,
            3000,
            0,
            0,
            0,
            0,
            0,
            0,
            0,
            0,
            0,
            0,
            0,
            0,
            0,
            0,
            0,
            0,
            3000,
            0,
            0,
            0,
            0,
            0,
            0,
            0,
            0
          ],
          "dynamic_selection_counts": [
            0,
            0,
            0,
            0,
            1565,
            14,
            0,
            1132,
            0,
            2203,
            1269,
            234,
            0,
            0,
            2040,
            1413,
            1110,
            421,
            39,
            2284,
            1352,
            1237,
            1,
            0,
            0,
            1119,
            0,
            436,
            0,
            0,
            45,
            86
          ]
        }
      }
    },
    {
      "epoch": 8,
      "layers": {
        "moe_0": {
          "selection_counts": [
            0,
            0,
            2,
            0,
            1371,
            0,
            3000,
            1207,
            0,
            2419,
            1263,
            258,
            3,
            0,
            2139,
            1476,
            1212,
            146,
            53,
            2460,
            1151,
            1228,
            1,
            3000,
            1,
            1045,
            0,
            473,
            0,
            1,
            67,
            24
          ],
          "fixed_selection_counts": [
            0,
            0,
            0,
            0,
            0,
            0,
            3000,
            0,
            0,
            0,
            0,
            0,
            0,
            0,
            0,
            0,
            0,
            0,
            0,
            0,
            0,
            0,
            0,
            3000,
            0,
            0,
            0,
            0,
            0,
            0,
            0,
            0
          ],
          "dynamic_selection_counts": [
            0,
            0,
            2,
            0,
            1371,
            0,
            0,
            1207,
            0,
            2419,
            1263,
            258,
            3,
            0,
            2139,
            1476,
            1212,
            146,
            53,
            2460,
            1151,
            1228,
            1,
            0,
            1,
            1045,
            0,
            473,
            0,
            1,
            67,
            24
          ]
        }
      }
    },
    {
      "epoch": 9,
      "layers": {
        "moe_0": {
          "selection_counts": [
            0,
            0,
            76,
            0,
            1411,
            0,
            3000,
            1018,
            0,
            2233,
            1540,
            164,
            0,
            0,
            2216,
            1414,
            1191,
            217,
            0,
            2378,
            1251,
            1159,
            2,
            3000,
            0,
            957,
            0,
            486,
            0,
            1,
            111,
            175
          ],
          "fixed_selection_counts": [
            0,
            0,
            0,
            0,
            0,
            0,
            3000,
            0,
            0,
            0,
            0,
            0,
            0,
            0,
            0,
            0,
            0,
            0,
            0,
            0,
            0,
            0,
            0,
            3000,
            0,
            0,
            0,
            0,
            0,
            0,
            0,
            0
          ],
          "dynamic_selection_counts": [
            0,
            0,
            76,
            0,
            1411,
            0,
            0,
            1018,
            0,
            2233,
            1540,
            164,
            0,
            0,
            2216,
            1414,
            1191,
            217,
            0,
            2378,
            1251,
            1159,
            2,
            0,
            0,
            957,
            0,
            486,
            0,
            1,
            111,
            175
          ]
        }
      }
    },
    {
      "epoch": 10,
      "layers": {
        "moe_0": {
          "selection_counts": [
            0,
            0,
            13,
            434,
            1526,
            0,
            3000,
            1213,
            0,
            2284,
            1405,
            160,
            4,
            0,
            2143,
            1446,
            1012,
            290,
            0,
            2030,
            1412,
            1209,
            0,
            3000,
            0,
            940,
            0,
            427,
            0,
            11,
            41,
            0
          ],
          "fixed_selection_counts": [
            0,
            0,
            0,
            0,
            0,
            0,
            3000,
            0,
            0,
            0,
            0,
            0,
            0,
            0,
            0,
            0,
            0,
            0,
            0,
            0,
            0,
            0,
            0,
            3000,
            0,
            0,
            0,
            0,
            0,
            0,
            0,
            0
          ],
          "dynamic_selection_counts": [
            0,
            0,
            13,
            434,
            1526,
            0,
            0,
            1213,
            0,
            2284,
            1405,
            160,
            4,
            0,
            2143,
            1446,
            1012,
            290,
            0,
            2030,
            1412,
            1209,
            0,
            0,
            0,
            940,
            0,
            427,
            0,
            11,
            41,
            0
          ]
        }
      }
    }
  ]
}