[
  {
    "epoch": 1,
    "train": {
      "loss": 1.430025684038798,
      "acc": 0.3826666664017571,
      "macro_f1": 0.37389538106606846,
      "routing_entropy": 1.8558020856645372
    },
    "val": {
      "loss": 1.444859209060669,
      "acc": 0.3839999930858612,
      "macro_f1": 0.3549823821334622,
      "routing_entropy": 1.9056697487831116
    },
    "test": {
      "loss": 1.429903190612793,
      "acc": 0.3979999992847443,
      "macro_f1": 0.3709500747962235,
      "routing_entropy": 1.9024720788002014
    },
    "expert_usage": {
      "moe_0": {
        "selection_counts": [
          9,
          1212,
          1235,
          1092,
          2300,
          3000,
          3000,
          152
        ],
        "fixed_selection_counts": [
          0,
          0,
          0,
          0,
          0,
          3000,
          3000,
          0
        ],
        "dynamic_selection_counts": [
          9,
          1212,
          1235,
          1092,
          2300,
          0,
          0,
          152
        ]
      }
    }
  },
  {
    "epoch": 2,
    "train": {
      "loss": 1.3255938448376126,
      "acc": 0.45600000026490956,
      "macro_f1": 0.4485070774116141,
      "routing_entropy": 1.7156210541725159
    },
    "val": {
      "loss": 1.498694408416748,
      "acc": 0.4279999897480011,
      "macro_f1": 0.4207243072490203,
      "routing_entropy": 1.607456088066101
    },
    "test": {
      "loss": 1.440884919166565,
      "acc": 0.3939999966621399,
      "macro_f1": 0.3798558233819075,
      "routing_entropy": 1.6218041777610779
    },
    "expert_usage": {
      "moe_0": {
        "selection_counts": [
          17,
          1091,
          1409,
          1020,
          2460,
          3000,
          3000,
          3
        ],
        "fixed_selection_counts": [
          0,
          0,
          0,
          0,
          0,
          3000,
          3000,
          0
        ],
        "dynamic_selection_counts": [
          17,
          1091,
          1409,
          1020,
          2460,
          0,
          0,
          3
        ]
      }
    }
  },
  {
    "epoch": 3,
    "train": {
      "loss": 1.2822639167573717,
      "acc": 0.4862222228315142,
      "macro_f1": 0.47407468521285656,
      "routing_entropy": 1.680013530784183
    },
    "val": {
      "loss": 1.4252603254318237,
      "acc": 0.3879999885559082,
      "macro_f1": 0.36265846096109555,
      "routing_entropy": 1.672719419002533
    },
    "test": {
      "loss": 1.3903410024642944,
      "acc": 0.4380000004768372,
      "macro_f1": 0.4046951027994744,
      "routing_entropy": 1.675073653459549
    },
    "expert_usage": {
      "moe_0": {
        "selection_counts": [
          10,
          951,
          1719,
          916,
          2396,
          3000,
          3000,
          8
        ],
        "fixed_selection_counts": [
          0,
          0,
          0,
          0,
          0,
          3000,
          3000,
          0
        ],
        "dynamic_selection_counts": [
          10,
          951,
          1719,
          916,
          2396,
          0,
          0,
          8
        ]
      }
    }
  },
  {
    "epoch": 4,
    "train": {
      "loss": 1.2541013181474474,
      "acc": 0.49377777814865115,
      "macro_f1": 0.4821513238275492,
      "routing_entropy": 1.6831308139695063
    },
    "val": {
      "loss": 1.3037381019592285,
      "acc": 0.4799999840259552,
      "macro_f1": 0.47699533440184094,
      "routing_entropy": 1.6717206239700317
    },
    "test": {
      "loss": 1.322057515144348,
      "acc": 0.43199999833106995,
      "macro_f1": 0.42717311117622037,
      "routing_entropy": 1.6719697415828705
    },
    "expert_usage": {
      "moe_0": {
        "selection_counts": [
          23,
          1216,
          1491,
          904,
          2346,
          3000,
          3000,
          20
        ],
        "fixed_selection_counts": [
          0,
          0,
          0,
          0,
          0,
          3000,
          3000,
          0
        ],
        "dynamic_selection_counts": [
          23,
          1216,
          1491,
          904,
          2346,
          0,
          0,
          20
        ]
      }
    }
  },
  {
    "epoch": 5,
    "train": {
      "loss": 1.2023839706844754,
      "acc": 0.5248888886239793,
      "macro_f1": 0.5170401273782256,
      "routing_entropy": 1.6425574488110013
    },
    "val": {
      "loss": 1.2147805442810058,
      "acc": 0.5479999904632569,
      "macro_f1": 0.5484033292136059,
      "routing_entropy": 1.5848222374916077
    },
    "test": {
      "loss": 1.226396764755249,
      "acc": 0.5060000002384186,
      "macro_f1": 0.5058945664466561,
      "routing_entropy": 1.5786304473876953
    },
    "expert_usage": {
      "moe_0": {
        "selection_counts": [
          30,
          1031,
          1538,
          881,
          2506,
          3000,
          3000,
          14
        ],
        "fixed_selection_counts": [
          0,
          0,
          0,
          0,
          0,
          3000,
          3000,
          0
        ],
        "dynamic_selection_counts": [
          30,
          1031,
          1538,
          881,
          2506,
          0,
          0,
          14
        ]
      }
    }
  },
  {
    "epoch": 6,
    "train": {
      "loss": 1.1851792074839274,
      "acc": 0.5133333336777157,
      "macro_f1": 0.5062415134275009,
      "routing_entropy": 1.618939095073276
    },
    "val": {
      "loss": 1.326312198638916,
      "acc": 0.5359999899864196,
      "macro_f1": 0.5285011172918747,
      "routing_entropy": 1.5543866753578186
    },
    "test": {
      "loss": 1.3174840488433839,
      "acc": 0.46000000071525576,
      "macro_f1": 0.4470817990758107,
      "routing_entropy": 1.5522280633449554
    },
    "expert_usage": {
      "moe_0": {
        "selection_counts": [
          13,
          1236,
          1490,
          918,
          2315,
          3000,
          3000,
          28
        ],
        "fixed_selection_counts": [
          0,
          0,
          0,
          0,
          0,
          3000,
          3000,
          0
        ],
        "dynamic_selection_counts": [
          13,
          1236,
          1490,
          918,
          2315,
          0,
          0,
          28
        ]
      }
    }
  },
  {
    "epoch": 7,
    "train": {
      "loss": 1.147186938603719,
      "acc": 0.5475555550257365,
      "macro_f1": 0.5410863525146848,
      "routing_entropy": 1.6220336821344163
    },
    "val": {
      "loss": 1.4060223999023438,
      "acc": 0.4479999957084656,
      "macro_f1": 0.4264947399202357,
      "routing_entropy": 1.577132225036621
    },
    "test": {
      "loss": 1.3877106838226319,
      "acc": 0.4640000026226044,
      "macro_f1": 0.452247903894034,
      "routing_entropy": 1.581784039735794
    },
    "expert_usage": {
      "moe_0": {
        "selection_counts": [
          8,
          908,
          1525,
          1008,
          2549,
          3000,
          3000,
          2
        ],
        "fixed_selection_counts": [
          0,
          0,
          0,
          0,
          0,
          3000,
          3000,
          0
        ],
        "dynamic_selection_counts": [
          8,
          908,
          1525,
          1008,
          2549,
          0,
          0,
          2
        ]
      }
    }
  },
  {
    "epoch": 8,
    "train": {
      "loss": 1.1167346267170377,
      "acc": 0.5560000012715658,
      "macro_f1": 0.5520554002442781,
      "routing_entropy": 1.6140642033682928
    },
    "val": {
      "loss": 1.2946352214813233,
      "acc": 0.491999981880188,
      "macro_f1": 0.4619353475275207,
      "routing_entropy": 1.5701889395713806
    },
    "test": {
      "loss": 1.2110102920532226,
      "acc": 0.5260000023841858,
      "macro_f1": 0.4913470480041499,
      "routing_entropy": 1.5765676498413086
    },
    "expert_usage": {
      "moe_0": {
        "selection_counts": [
          8,
          582,
          1536,
          1279,
          2595,
          3000,
          3000,
          0
        ],
        "fixed_selection_counts": [
          0,
          0,
          0,
          0,
          0,
          3000,
          3000,
          0
        ],
        "dynamic_selection_counts": [
          8,
          582,
          1536,
          1279,
          2595,
          0,
          0,
          0
        ]
      }
    }
  },
  {
    "epoch": 9,
    "train": {
      "loss": 1.12689993625217,
      "acc": 0.5555555555555556,
      "macro_f1": 0.5526289480417862,
      "routing_entropy": 1.5978869729571872
    },
    "val": {
      "loss": 1.1303308787345887,
      "acc": 0.5679999775886536,
      "macro_f1": 0.558348256202241,
      "routing_entropy": 1.503774106502533
    },
    "test": {
      "loss": 1.1635151567459106,
      "acc": 0.5520000042915344,
      "macro_f1": 0.538779833249494,
      "routing_entropy": 1.5114222466945648
    },
    "expert_usage": {
      "moe_0": {
        "selection_counts": [
          3,
          682,
          1503,
          1212,
          2600,
          3000,
          3000,
          0
        ],
        "fixed_selection_counts": [
          0,
          0,
          0,
          0,
          0,
          3000,
          3000,
          0
        ],
        "dynamic_selection_counts": [
          3,
          682,
          1503,
          1212,
          2600,
          0,
          0,
          0
        ]
      }
    }
  },
  {
    "epoch": 10,
    "train": {
      "loss": 1.0950702089733548,
      "acc": 0.5733333334128062,
      "macro_f1": 0.5676924127338001,
      "routing_entropy": 1.6211725738313463
    },
    "val": {
      "loss": 1.1884959955215455,
      "acc": 0.5439999761581421,
      "macro_f1": 0.534497603369946,
      "routing_entropy": 1.5632448196411133
    },
    "test": {
      "loss": 1.1847795581817626,
      "acc": 0.5120000002384186,
      "macro_f1": 0.5064946682132887,
      "routing_entropy": 1.5607568323612213
    },
    "expert_usage": {
      "moe_0": {
        "selection_counts": [
          1,
          1174,
          1363,
          852,
          2610,
          3000,
          3000,
          0
        ],
        "fixed_selection_counts": [
          0,
          0,
          0,
          0,
          0,
          3000,
          3000,
          0
        ],
        "dynamic_selection_counts": [
          1,
          1174,
          1363,
          852,
          2610,
          0,
          0,
          0
        ]
      }
    }
  }
]